haishoku/__init__.py
haishoku/alg.py
haishoku/haillow.py
haishoku/haishoku.py
haishoku-1.1.8.dist-info/DESCRIPTION.rst
haishoku-1.1.8.dist-info/METADATA
haishoku-1.1.8.dist-info/RECORD
haishoku-1.1.8.dist-info/WHEEL
haishoku-1.1.8.dist-info/metadata.json
haishoku-1.1.8.dist-info/top_level.txt
